hardware_heartbeat/__init__.py
hardware_heartbeat/__main__.py
hardware_heartbeat/server.py
hardware_heartbeat-0.1.0.dist-info/METADATA
hardware_heartbeat-0.1.0.dist-info/WHEEL
hardware_heartbeat-0.1.0.dist-info/entry_points.txt
hardware_heartbeat-0.1.0.dist-info/RECORD
