Metadata-Version: 2.4
Name: hardware_heartbeat
Version: 0.1.0
Summary: Add your description here
Requires-Python: >=3.12
Requires-Dist: mcp[cli]>=1.15.0
Requires-Dist: psutil>=5.9.0
